pynose_exclude
