Metadata-Version: 2.1
Name: pynose-exclude
Version: 1.0.1
Summary: Exclude specific directories from pynose runs.
Home-page: https://github.com/nyefan/pynose-exclude
Author: Nyefan
Author-email: pynose-exclude@nyefan.org
License: GNU LGPL
Classifier: Development Status :: 5 - Production/Stable
Classifier: Intended Audience :: Developers
Classifier: License :: OSI Approved :: GNU Library or Lesser General Public License (LGPL)
Classifier: Topic :: Software Development :: Testing
Classifier: Programming Language :: Python
License-File: LICENSE
License-File: AUTHORS
Requires-Dist: pynose
